Metadata-Version: 2.1
Name: remoroo
Version: 0.2.11
Summary: Remoroo Offline Engine CLI
Requires-Python: >=3.9
Requires-Dist: typer>=0.9.0
Requires-Dist: jsonschema>=4.22.0
Requires-Dist: requests>=2.31.0
Requires-Dist: remoroo-core>=0.1.1
Requires-Dist: sseclient-py
Requires-Dist: prompt-toolkit>=3.0.0
